la_mancha/__init__.py
la_mancha/types.py
etna_quixote_la_mancha-1.0.0.dist-info/LICENSE
etna_quixote_la_mancha-1.0.0.dist-info/METADATA
etna_quixote_la_mancha-1.0.0.dist-info/WHEEL
etna_quixote_la_mancha-1.0.0.dist-info/top_level.txt
etna_quixote_la_mancha-1.0.0.dist-info/RECORD
