Metadata-Version: 2.1
Name: etna-quixote-la-mancha
Version: 1.0.0
Summary: Addition to Quixote to deal with La Mancha
Home-page: https://github.com/etna-alternance/etna-quixote-la-mancha
Author: Clément Doumergue
Author-email: clement.doumergue@etna.io
License: UNKNOWN
Platform: UNKNOWN
Classifier: Programming Language :: Python :: 3
Classifier: License :: OSI Approved :: MIT License
Classifier: Operating System :: OS Independent
